xdlake/__init__.py
xdlake/__version__.py
xdlake/dataset_utils.py
xdlake/storage.py
xdlake/utils.py
xdlake/delta_log/__init__.py
xdlake/delta_log/actions.py
xdlake/delta_log/schema.py
xdlake/delta_log/statistics.py
xdlake-0.0.10.dist-info/LICENSE
xdlake-0.0.10.dist-info/METADATA
xdlake-0.0.10.dist-info/WHEEL
xdlake-0.0.10.dist-info/top_level.txt
xdlake-0.0.10.dist-info/RECORD
