Metadata-Version: 2.1
Name: xdlake
Version: 0.0.10
Summary: A loose implimentation of the deltalake spec focused on extensibility and distributed data.
Author-email: Brian Hannafious <xbrianh@amorphous-industries.com>
License: MIT
Project-URL: Homepage, https://github.com/xbrianh/xdlake
Project-URL: Repository, https://github.com/xbrianh/xdlake.git
Project-URL: Issues, https://github.com/xbrianh/xdlake/issues
Keywords: deltalake,parquet
Classifier: Programming Language :: Python :: 3
Classifier: Programming Language :: Python :: 3.10
Classifier: Programming Language :: Python :: 3.11
Classifier: Programming Language :: Python :: 3.12
Classifier: License :: OSI Approved :: MIT License
Classifier: Operating System :: OS Independent
Requires-Python: >=3.10
License-File: LICENSE
Requires-Dist: pyarrow
Requires-Dist: fsspec
